[
  {
    "id": "tip001",
    "title": "如何判断守宫是否吃饱",
    "content": "观察守宫的腹部，如果腹部鼓起来且圆润，说明已经吃饱。一般幼体每天喂食，成体每2-3天喂食一次。",
    "category_id": "care_feeding",
    "tags": ["守宫", "喂食", "判断"],
    "created_at": "2024-01-01T00:00:00.000Z"
  },
  {
    "id": "tip002",
    "title": "爬宠洗澡的正确方法",
    "content": "使用温水（约30度），水深不超过爬宠高度的一半。轻轻清洗，避免水进入口鼻。洗澡后务必擦干并保持温暖。",
    "category_id": "care_daily",
    "tags": ["洗澡", "护理", "方法"],
    "created_at": "2024-01-01T00:00:00.000Z"
  },
  {
    "id": "tip003",
    "title": "如何安全抓取蛇类",
    "content": "从侧面轻轻把手放在蛇身下支撑，让蛇感觉到你的手再慢慢拿起。避免从上方突然抓取，这会让蛇感到威胁。",
    "category_id": "care_daily",
    "tags": ["蛇", "抓取", "安全"],
    "created_at": "2024-01-01T00:00:00.000Z"
  },
  {
    "id": "tip004",
    "title": "如何给守宫补充钙质",
    "content": "在食盆中放少量钙粉，让守宫自行舔食。每周可喂食1-2次带钙粉的蟋蟀。钙粉建议选择含D3的。",
    "category_id": "care_feeding",
    "tags": ["守宫", "钙粉", "营养"],
    "created_at": "2024-01-01T00:00:00.000Z"
  },
  {
    "id": "tip005",
    "title": "判断陆龟是否健康",
    "content": "观察陆龟的甲壳是否坚硬、眼睛是否明亮有神、鼻孔是否通畅、肛门是否干净。健康的陆龟应该爬行积极、食欲良好。",
    "category_id": "health_prevent",
    "tags": ["陆龟", "健康", "检查"],
    "created_at": "2024-01-01T00:00:00.000Z"
  },
  {
    "id": "tip006",
    "title": "爬宠蜕皮期护理",
    "content": "蜕皮期间保持适度湿度，可适当喷雾。提供粗糙物体帮助蜕皮。不要强行拉扯未脱落的皮，以免造成伤害。",
    "category_id": "care_daily",
    "tags": ["蜕皮", "护理", "方法"],
    "created_at": "2024-01-01T00:00:00.000Z"
  },
  {
    "id": "tip007",
    "title": "如何让蛇类开食",
    "content": "新买的蛇类先静养2-3天再喂食。可尝试用活鼠引诱，或将鼠在温水中浸泡后投喂。保持饲养箱安静，光线昏暗。",
    "category_id": "care_feeding",
    "tags": ["蛇", "开食", "方法"],
    "created_at": "2024-01-01T00:00:00.000Z"
  },
  {
    "id": "tip008",
    "title": "鬃狮蜥饲料昆虫大小选择",
    "content": "昆虫宽度不应超过鬃狮蜥两眼之间的距离。幼体喂食针头蟋蟀，成体可喂食杜比亚蟑螂或大麦虫。",
    "category_id": "care_feeding",
    "tags": ["鬃狮蜥", "昆虫", "大小"],
    "created_at": "2024-01-01T00:00:00.000Z"
  },
  {
    "id": "tip009",
    "title": "龟类晒背注意事项",
    "content": "提供晒背平台，让龟可以完全离开水面。避免阳光直射导致过热，可设置阴凉处。使用UVB灯也可满足需求。",
    "category_id": "care_housing",
    "tags": ["龟", "晒背", "UVB"],
    "created_at": "2024-01-01T00:00:00.000Z"
  },
  {
    "id": "tip010",
    "title": "如何清洁饲养箱",
    "content": "日常清洁：清除粪便和剩余食物。每周：更换垫材、清洁造景物品。每月：彻底消毒，使用宠物安全的消毒剂。",
    "category_id": "care_daily",
    "tags": ["清洁", "卫生", "方法"],
    "created_at": "2024-01-01T00:00:00.000Z"
  }
]
